<?xml version="1.0" encoding="UTF-8"?>
<services xmlns:xsi="http://www.w3.org/2001/XMLSchema-instance" xsi:noNamespaceSchemaLocation="http://moqui.org/xsd/service-definition-3.xsd">
    <service verb="create" noun="Party" type="entity-auto">
        <in-parameters>
            <auto-parameters entity-name="Party" include="nonpk"/>
            <parameter name="partyType" required="true"/>
        </in-parameters>
        <out-parameters><parameter name="partyId"/></out-parameters>
    </service>

    <service verb="create" noun="OrderHeader2">
        <in-parameters>
            <auto-parameters entity-name="OrderHeader" include="nonpk"/>
            <auto-parameters entity-name="OrderItem" include="nonpk"/>
        </in-parameters>
        <out-parameters>
            <parameter name="oderId"/>
            <parameter name="oderItemSequenceId"/>
        </out-parameters>
        <actions>
            <service-call name="create#OrderHeader" in-map="context" out-map="context"/>
            <service-call name="create#OrderItem" in-map="context" out-map="context"/>

        </actions>
    </service>

    <service verb="delete" noun="OrderHeader">
        <in-parameters>
            <parameter name="orderId" required="true"/>
        </in-parameters>

        <actions>
            <entity-find-one entity-name="OrderHeader" value-field="orderInfo"/>
            <entity-delete-related value-field="orderInfo"  relationship-name="OrderHeader#tutorial.OrderItem"/>
            <entity-delete-by-condition entity-name="OrderHeader" >
                <econdition field-name="orderId"/>
            </entity-delete-by-condition>
        </actions>
    </service>







    <service verb="find" noun="OrderHeader" >
    <in-parameters>
        <parameter name="orderId" required="true"/>
    </in-parameters>
    <out-parameters>
        <parameter name="orderInfo" type="list"/>
        <parameter name="orderItemInfo" type="list"/>
        <parameter name="partyInfo" type="list"/>
        <parameter name="shippingInfo" type="list"/>
        <parameter name="contactInfo" type="list"/>
    </out-parameters>
        <actions>
            <entity-find-one entity-name="OrderHeader" value-field="orderInfo">
                  <field-map field-name="orderId" from="orderId"/>
            </entity-find-one>
            <entity-find entity-name="OrderItem" list="orderItemInfo">
                <econdition field-name="orderId"/>
            </entity-find>
            <entity-find-one entity-name="Party" value-field="partyInfo">
                <field-map field-name="partyId" from="orderInfo.partyId"/>
            </entity-find-one>
            <entity-find-one entity-name="ContactMech" value-field="shippingInfo">
                <field-map field-name="contactMechId" from="orderInfo.shippingContactMechId"/>
            </entity-find-one>
            <entity-find-one entity-name="ContactMech" value-field="contactInfo">
                <field-map field-name="contactMechId" from="orderInfo.shippingContactMechId"/>
            </entity-find-one>

        </actions>
    </service>





    <service verb="delete" noun="Product">
        <in-parameters>
            <parameter name="productId" required="true"/>
        </in-parameters>

        <actions>
            <entity-find-one entity-name="Product" value-field="productInfo"/>
            <entity-delete-related value-field="productInfo"  relationship-name="Product#tutorial.OrderItem"/>
            <entity-delete-by-condition entity-name="Product" >
                <econdition field-name="productId"/>
            </entity-delete-by-condition>
        </actions>
    </service>

<!--    <service verb="delete" noun="Party">-->
<!--        <in-parameters>-->
<!--            <parameter name="partyId" required="true"/>-->
<!--        </in-parameters>-->

<!--        <actions>-->
<!--            <entity-find-one entity-name="Party" value-field="partyInfo"/>-->
<!--            <entity-delete-related value-field="partyInfo"  relationship-name="Party#tutorial.ContactMech"/>-->
<!--            <entity-delete-related value-field="partyInfo"  relationship-name="BillingContactMech#tutorial.OrderHeader"/>-->
<!--            <entity-delete-related value-field="partyInfo"  relationship-name="OrderHeader#tutorial.OrderItem"/>-->
<!--            <entity-delete-related value-field="partyInfo"  relationship-name="ShippingContactMech#tutorial.OrderHeader"/>-->
<!--            <entity-delete-related value-field="partyInfo"  relationship-name="Party#tutorial.OrderHeade"/>-->
<!--            <entity-delete-by-condition entity-name="Party" >-->
<!--                <econdition field-name="partyId"/>-->
<!--            </entity-delete-by-condition>-->
<!--        </actions>-->
<!--    </service>-->

</services>